{
    "id": 17,
    "length": 22144,
    "strings": [
        {
            "str": "安全",
            "blen": 4,
            "memory_address": 35958404,
            "xrefs": [
                19564
            ]
        },
        {
            "str": "安全",
            "blen": 4,
            "memory_address": 35958412,
            "xrefs": [
                19988
            ]
        },
        {
            "str": "安全",
            "blen": 4,
            "memory_address": 35958420,
            "xrefs": [
                19140
            ]
        },
        {
            "str": "安全",
            "blen": 4,
            "memory_address": 35958428,
            "xrefs": [
                17868
            ]
        },
        {
            "str": "安全",
            "blen": 4,
            "memory_address": 35958436,
            "xrefs": [
                18716
            ]
        },
        {
            "str": "安全",
            "blen": 4,
            "memory_address": 35958444,
            "xrefs": [
                18292
            ]
        },
        {
            "str": "安全",
            "blen": 4,
            "memory_address": 35958452,
            "xrefs": [
                20412
            ]
        },
        {
            "str": "新鮮さ",
            "blen": 6,
            "memory_address": 35958468,
            "xrefs": [
                17852
            ]
        },
        {
            "str": "温かさ",
            "blen": 6,
            "memory_address": 35958476,
            "xrefs": [
                19116
            ]
        },
        {
            "str": "新鮮さ",
            "blen": 6,
            "memory_address": 35958484,
            "xrefs": [
                19548
            ]
        },
        {
            "str": "新鮮さ",
            "blen": 6,
            "memory_address": 35958492,
            "xrefs": [
                20396
            ]
        },
        {
            "str": "温かさ",
            "blen": 6,
            "memory_address": 35958500,
            "xrefs": [
                18268
            ]
        },
        {
            "str": "温かさ",
            "blen": 6,
            "memory_address": 35958508,
            "xrefs": [
                20388
            ]
        },
        {
            "str": "新鮮さ",
            "blen": 6,
            "memory_address": 35958516,
            "xrefs": [
                18700
            ]
        },
        {
            "str": "温かさ",
            "blen": 6,
            "memory_address": 35958524,
            "xrefs": [
                17844
            ]
        },
        {
            "str": "温かさ",
            "blen": 6,
            "memory_address": 35958532,
            "xrefs": [
                19964
            ]
        },
        {
            "str": "新鮮さ",
            "blen": 6,
            "memory_address": 35958540,
            "xrefs": [
                18276
            ]
        },
        {
            "str": "新鮮さ",
            "blen": 6,
            "memory_address": 35958548,
            "xrefs": [
                19124
            ]
        },
        {
            "str": "新鮮さ",
            "blen": 6,
            "memory_address": 35958556,
            "xrefs": [
                19972
            ]
        },
        {
            "str": "温かさ",
            "blen": 6,
            "memory_address": 35958564,
            "xrefs": [
                19540
            ]
        },
        {
            "str": "温かさ",
            "blen": 6,
            "memory_address": 35958572,
            "xrefs": [
                18692
            ]
        },
        {
            "str": "エッグ",
            "blen": 6,
            "memory_address": 35958580,
            "xrefs": [
                15284
            ]
        },
        {
            "str": "１７７℃",
            "blen": 8,
            "memory_address": 35959280,
            "xrefs": [
                17532
            ]
        },
        {
            "str": "１７７℃",
            "blen": 8,
            "memory_address": 35959292,
            "xrefs": [
                17108
            ]
        },
        {
            "str": "１７７℃",
            "blen": 8,
            "memory_address": 35959304,
            "xrefs": [
                16684
            ]
        },
        {
            "str": "２１８℃",
            "blen": 8,
            "memory_address": 35959316,
            "xrefs": [
                17480
            ]
        },
        {
            "str": "２１８℃",
            "blen": 8,
            "memory_address": 35959328,
            "xrefs": [
                16632
            ]
        },
        {
            "str": "１７７℃",
            "blen": 8,
            "memory_address": 35959340,
            "xrefs": [
                15836
            ]
        },
        {
            "str": "１６８℃",
            "blen": 8,
            "memory_address": 35959352,
            "xrefs": [
                13664
            ]
        },
        {
            "str": "アツアツ",
            "blen": 8,
            "memory_address": 35959364,
            "xrefs": [
                16572
            ]
        },
        {
            "str": "アツアツ",
            "blen": 8,
            "memory_address": 35959376,
            "xrefs": [
                16148
            ]
        },
        {
            "str": "（目安）",
            "blen": 8,
            "memory_address": 35959388,
            "xrefs": [
                16728
            ]
        },
        {
            "str": "１３５℃",
            "blen": 8,
            "memory_address": 35959400,
            "xrefs": [
                16200
            ]
        },
        {
            "str": "（目安）",
            "blen": 8,
            "memory_address": 35959436,
            "xrefs": [
                15880
            ]
        },
        {
            "str": "（目安）",
            "blen": 8,
            "memory_address": 35959448,
            "xrefs": [
                17576
            ]
        },
        {
            "str": "アツアツ",
            "blen": 8,
            "memory_address": 35959460,
            "xrefs": [
                17420
            ]
        },
        {
            "str": "アツアツ",
            "blen": 8,
            "memory_address": 35959472,
            "xrefs": [
                15724
            ]
        },
        {
            "str": "２１８℃",
            "blen": 8,
            "memory_address": 35959484,
            "xrefs": [
                17056
            ]
        },
        {
            "str": "１６６℃",
            "blen": 8,
            "memory_address": 35959496,
            "xrefs": [
                20872
            ]
        },
        {
            "str": "１８２℃",
            "blen": 8,
            "memory_address": 35959508,
            "xrefs": [
                14088
            ]
        },
        {
            "str": "アツアツ",
            "blen": 8,
            "memory_address": 35959520,
            "xrefs": [
                16996
            ]
        },
        {
            "str": "２１８℃",
            "blen": 8,
            "memory_address": 35959532,
            "xrefs": [
                15784
            ]
        },
        {
            "str": "グリル温度",
            "blen": 10,
            "memory_address": 35959544,
            "xrefs": [
                17092
            ]
        },
        {
            "str": "ジューシー",
            "blen": 10,
            "memory_address": 35959556,
            "xrefs": [
                17428
            ]
        },
        {
            "str": "正しく焼成",
            "blen": 10,
            "memory_address": 35959568,
            "xrefs": [
                17012
            ]
        },
        {
            "str": "正しい調理",
            "blen": 10,
            "memory_address": 35959580,
            "xrefs": [
                14876
            ]
        },
        {
            "str": "ジューシー",
            "blen": 10,
            "memory_address": 35959592,
            "xrefs": [
                16580
            ]
        },
        {
            "str": "フルバッグ",
            "blen": 10,
            "memory_address": 35959604,
            "xrefs": [
                13620
            ]
        },
        {
            "str": "正しい調理",
            "blen": 10,
            "memory_address": 35959616,
            "xrefs": [
                20828
            ]
        },
        {
            "str": "正しく焼成",
            "blen": 10,
            "memory_address": 35959628,
            "xrefs": [
                17436
            ]
        },
        {
            "str": "正しく焼成",
            "blen": 10,
            "memory_address": 35959640,
            "xrefs": [
                15316
            ]
        },
        {
            "str": "ジューシー",
            "blen": 10,
            "memory_address": 35959652,
            "xrefs": [
                15732
            ]
        },
        {
            "str": "正しく焼成",
            "blen": 10,
            "memory_address": 35959664,
            "xrefs": [
                15740
            ]
        },
        {
            "str": "ジューシー",
            "blen": 10,
            "memory_address": 35959676,
            "xrefs": [
                17004
            ]
        },
        {
            "str": "グリル温度",
            "blen": 10,
            "memory_address": 35959688,
            "xrefs": [
                15820
            ]
        },
        {
            "str": "正しく焼成",
            "blen": 10,
            "memory_address": 35959700,
            "xrefs": [
                16156
            ]
        },
        {
            "str": "グリル温度",
            "blen": 10,
            "memory_address": 35959712,
            "xrefs": [
                17516
            ]
        },
        {
            "str": "正しく焼成",
            "blen": 10,
            "memory_address": 35959724,
            "xrefs": [
                16588
            ]
        },
        {
            "str": "グリル温度",
            "blen": 10,
            "memory_address": 35959736,
            "xrefs": [
                16668
            ]
        },
        {
            "str": "程よい塩加減",
            "blen": 12,
            "memory_address": 35959748,
            "xrefs": [
                13612
            ]
        },
        {
            "str": "４：１パティ",
            "blen": 12,
            "memory_address": 35959764,
            "xrefs": [
                17048
            ]
        },
        {
            "str": "プラテン温度",
            "blen": 12,
            "memory_address": 35959780,
            "xrefs": [
                16616
            ]
        },
        {
            "str": "４：１パティ",
            "blen": 12,
            "memory_address": 35959796,
            "xrefs": [
                17100
            ]
        },
        {
            "str": "スタンダード",
            "blen": 12,
            "memory_address": 35959812,
            "xrefs": [
                14928
            ]
        },
        {
            "str": "スピーディー",
            "blen": 12,
            "memory_address": 35959828,
            "xrefs": [
                21660
            ]
        },
        {
            "str": "エクステンド",
            "blen": 12,
            "memory_address": 35959844,
            "xrefs": [
                14936
            ]
        },
        {
            "str": "卵は室温か？",
            "blen": 12,
            "memory_address": 35959860,
            "xrefs": [
                14972
            ]
        },
        {
            "str": "スピーディー",
            "blen": 12,
            "memory_address": 35959876,
            "xrefs": [
                21236
            ]
        },
        {
            "str": "プラテン温度",
            "blen": 12,
            "memory_address": 35959892,
            "xrefs": [
                15768
            ]
        },
        {
            "str": "プラテン温度",
            "blen": 12,
            "memory_address": 35959908,
            "xrefs": [
                17040
            ]
        },
        {
            "str": "外はカリカリ",
            "blen": 12,
            "memory_address": 35959924,
            "xrefs": [
                14036
            ]
        },
        {
            "str": "ビッグマック",
            "blen": 12,
            "memory_address": 35959940,
            "xrefs": [
                19100
            ]
        },
        {
            "str": "４：１パティ",
            "blen": 12,
            "memory_address": 35959956,
            "xrefs": [
                17404
            ]
        },
        {
            "str": "プラテン温度",
            "blen": 12,
            "memory_address": 35959972,
            "xrefs": [
                17464
            ]
        },
        {
            "str": "フライヤー温度",
            "blen": 14,
            "memory_address": 35959988,
            "xrefs": [
                13648
            ]
        },
        {
            "str": "ドライブスルー",
            "blen": 14,
            "memory_address": 35960004,
            "xrefs": [
                22068
            ]
        },
        {
            "str": "見た目の美しさ",
            "blen": 14,
            "memory_address": 35960020,
            "xrefs": [
                19556
            ]
        },
        {
            "str": "プレップタイム",
            "blen": 14,
            "memory_address": 35960036,
            "xrefs": [
                19584
            ]
        },
        {
            "str": "ハッシュポテト",
            "blen": 14,
            "memory_address": 35960052,
            "xrefs": [
                14436
            ]
        },
        {
            "str": "見た目の美しさ",
            "blen": 14,
            "memory_address": 35960068,
            "xrefs": [
                19980
            ]
        },
        {
            "str": "正確な取り揃え",
            "blen": 14,
            "memory_address": 35960084,
            "xrefs": [
                21244
            ]
        },
        {
            "str": "見た目の美しさ",
            "blen": 14,
            "memory_address": 35960100,
            "xrefs": [
                20404
            ]
        },
        {
            "str": "ハッシュポテト",
            "blen": 14,
            "memory_address": 35960116,
            "xrefs": [
                14080
            ]
        },
        {
            "str": "プレップタイム",
            "blen": 14,
            "memory_address": 35960132,
            "xrefs": [
                20008
            ]
        },
        {
            "str": "正確な取り揃え",
            "blen": 14,
            "memory_address": 35960148,
            "xrefs": [
                21668
            ]
        },
        {
            "str": "お客様への礼儀",
            "blen": 14,
            "memory_address": 35960164,
            "xrefs": [
                14444
            ]
        },
        {
            "str": "プレップタイム",
            "blen": 14,
            "memory_address": 35960180,
            "xrefs": [
                17888
            ]
        },
        {
            "str": "ロット＆ロビー",
            "blen": 14,
            "memory_address": 35960196,
            "xrefs": [
                14860
            ]
        },
        {
            "str": "見た目の美しさ",
            "blen": 14,
            "memory_address": 35960212,
            "xrefs": [
                18284
            ]
        },
        {
            "str": "程よい焼きムラ",
            "blen": 14,
            "memory_address": 35960228,
            "xrefs": [
                15300
            ]
        },
        {
            "str": "プレップタイム",
            "blen": 14,
            "memory_address": 35960244,
            "xrefs": [
                18312
            ]
        },
        {
            "str": "見た目の美しさ",
            "blen": 14,
            "memory_address": 35960260,
            "xrefs": [
                17860
            ]
        },
        {
            "str": "チーズバーガー",
            "blen": 14,
            "memory_address": 35960276,
            "xrefs": [
                18676
            ]
        },
        {
            "str": "ＳＡＵＳＡＧＥ",
            "blen": 14,
            "memory_address": 35960292,
            "xrefs": [
                15776
            ]
        },
        {
            "str": "ＳＡＵＳＡＧＥ",
            "blen": 14,
            "memory_address": 35960308,
            "xrefs": [
                15828
            ]
        },
        {
            "str": "見た目の美しさ",
            "blen": 14,
            "memory_address": 35960324,
            "xrefs": [
                18708
            ]
        },
        {
            "str": "プレップタイム",
            "blen": 14,
            "memory_address": 35960340,
            "xrefs": [
                20432
            ]
        },
        {
            "str": "プレップタイム",
            "blen": 14,
            "memory_address": 35960356,
            "xrefs": [
                18736
            ]
        },
        {
            "str": "フライヤー温度",
            "blen": 14,
            "memory_address": 35960372,
            "xrefs": [
                14072
            ]
        },
        {
            "str": "フライヤー温度",
            "blen": 14,
            "memory_address": 35960388,
            "xrefs": [
                20856
            ]
        },
        {
            "str": "てりやきパティ",
            "blen": 14,
            "memory_address": 35960404,
            "xrefs": [
                17828
            ]
        },
        {
            "str": "１０：１パティ",
            "blen": 14,
            "memory_address": 35960420,
            "xrefs": [
                16980
            ]
        },
        {
            "str": "お客様への礼儀",
            "blen": 14,
            "memory_address": 35960436,
            "xrefs": [
                14496
            ]
        },
        {
            "str": "ＲＥＧ／ＭＡＣ",
            "blen": 14,
            "memory_address": 35960452,
            "xrefs": [
                16624
            ]
        },
        {
            "str": "見た目の美しさ",
            "blen": 14,
            "memory_address": 35960468,
            "xrefs": [
                19132
            ]
        },
        {
            "str": "ＲＥＧ／ＭＡＣ",
            "blen": 14,
            "memory_address": 35960484,
            "xrefs": [
                16676
            ]
        },
        {
            "str": "プレップタイム",
            "blen": 14,
            "memory_address": 35960500,
            "xrefs": [
                19160
            ]
        },
        {
            "str": "クッキングタイム",
            "blen": 16,
            "memory_address": 35960516,
            "xrefs": [
                13700
            ]
        },
        {
            "str": "クッキングタイム",
            "blen": 16,
            "memory_address": 35960536,
            "xrefs": [
                20908
            ]
        },
        {
            "str": "クッキングタイム",
            "blen": 16,
            "memory_address": 35960556,
            "xrefs": [
                17144
            ]
        },
        {
            "str": "作業前に手を洗う",
            "blen": 16,
            "memory_address": 35960576,
            "xrefs": [
                17196
            ]
        },
        {
            "str": "作業前に手を洗う",
            "blen": 16,
            "memory_address": 35960596,
            "xrefs": [
                19264
            ]
        },
        {
            "str": "作業前に手を洗う",
            "blen": 16,
            "memory_address": 35960616,
            "xrefs": [
                21808
            ]
        },
        {
            "str": "作業前に手を洗う",
            "blen": 16,
            "memory_address": 35960636,
            "xrefs": [
                19688
            ]
        },
        {
            "str": "ＴＥＲＩＹＡＫＩ",
            "blen": 16,
            "memory_address": 35960656,
            "xrefs": [
                17472
            ]
        },
        {
            "str": "作業前に手を洗う",
            "blen": 16,
            "memory_address": 35960676,
            "xrefs": [
                20960
            ]
        },
        {
            "str": "ＴＥＲＩＹＡＫＩ",
            "blen": 16,
            "memory_address": 35960696,
            "xrefs": [
                17524
            ]
        },
        {
            "str": "クッキングタイム",
            "blen": 16,
            "memory_address": 35960716,
            "xrefs": [
                17568
            ]
        },
        {
            "str": "作業前に手を洗う",
            "blen": 16,
            "memory_address": 35960736,
            "xrefs": [
                17620
            ]
        },
        {
            "str": "作業前に手を洗う",
            "blen": 16,
            "memory_address": 35960756,
            "xrefs": [
                13804
            ]
        },
        {
            "str": "クッキングタイム",
            "blen": 16,
            "memory_address": 35960776,
            "xrefs": [
                14124
            ]
        },
        {
            "str": "作業前に手を洗う",
            "blen": 16,
            "memory_address": 35960796,
            "xrefs": [
                14176
            ]
        },
        {
            "str": "作業前に手を洗う",
            "blen": 16,
            "memory_address": 35960816,
            "xrefs": [
                20112
            ]
        },
        {
            "str": "作業前に手を洗う",
            "blen": 16,
            "memory_address": 35960836,
            "xrefs": [
                17992
            ]
        },
        {
            "str": "クッキングタイム",
            "blen": 16,
            "memory_address": 35960856,
            "xrefs": [
                16720
            ]
        },
        {
            "str": "クッキングタイム",
            "blen": 16,
            "memory_address": 35960876,
            "xrefs": [
                14920
            ]
        },
        {
            "str": "作業前に手を洗う",
            "blen": 16,
            "memory_address": 35960896,
            "xrefs": [
                15024
            ]
        },
        {
            "str": "カリッとした食感",
            "blen": 16,
            "memory_address": 35960916,
            "xrefs": [
                15308
            ]
        },
        {
            "str": "クッキングタイム",
            "blen": 16,
            "memory_address": 35960936,
            "xrefs": [
                15344
            ]
        },
        {
            "str": "作業前に手を洗う",
            "blen": 16,
            "memory_address": 35960956,
            "xrefs": [
                21384
            ]
        },
        {
            "str": "作業前に手を洗う",
            "blen": 16,
            "memory_address": 35960976,
            "xrefs": [
                18416
            ]
        },
        {
            "str": "作業前に手を洗う",
            "blen": 16,
            "memory_address": 35960996,
            "xrefs": [
                15448
            ]
        },
        {
            "str": "作業前に手を洗う",
            "blen": 16,
            "memory_address": 35961016,
            "xrefs": [
                16772
            ]
        },
        {
            "str": "クッキングタイム",
            "blen": 16,
            "memory_address": 35961036,
            "xrefs": [
                15872
            ]
        },
        {
            "str": "作業前に手を洗う",
            "blen": 16,
            "memory_address": 35961056,
            "xrefs": [
                15924
            ]
        },
        {
            "str": "ソーセージパティ",
            "blen": 16,
            "memory_address": 35961076,
            "xrefs": [
                16132
            ]
        },
        {
            "str": "作業前に手を洗う",
            "blen": 16,
            "memory_address": 35961096,
            "xrefs": [
                20536
            ]
        },
        {
            "str": "作業前に手を洗う",
            "blen": 16,
            "memory_address": 35961116,
            "xrefs": [
                18840
            ]
        },
        {
            "str": "作業前に手を洗う",
            "blen": 16,
            "memory_address": 35961136,
            "xrefs": [
                16244
            ]
        },
        {
            "str": "フィレオフィッシュ",
            "blen": 18,
            "memory_address": 35961156,
            "xrefs": [
                20864
            ]
        },
        {
            "str": "マネージャーに確認",
            "blen": 18,
            "memory_address": 35961176,
            "xrefs": [
                17152
            ]
        },
        {
            "str": "フロントカウンター",
            "blen": 18,
            "memory_address": 35961196,
            "xrefs": [
                21644
            ]
        },
        {
            "str": "マックフライポテト",
            "blen": 18,
            "memory_address": 35961216,
            "xrefs": [
                13656
            ]
        },
        {
            "str": "ポテトのサイズと量",
            "blen": 18,
            "memory_address": 35961236,
            "xrefs": [
                13752
            ]
        },
        {
            "str": "マックフライポテト",
            "blen": 18,
            "memory_address": 35961256,
            "xrefs": [
                14012
            ]
        },
        {
            "str": "ゴールデンブラウン",
            "blen": 18,
            "memory_address": 35961276,
            "xrefs": [
                14044
            ]
        },
        {
            "str": "形がくずれていない",
            "blen": 18,
            "memory_address": 35961296,
            "xrefs": [
                14884
            ]
        },
        {
            "str": "フレンドリーな対応",
            "blen": 18,
            "memory_address": 35961316,
            "xrefs": [
                21252
            ]
        },
        {
            "str": "フレンドリーな対応",
            "blen": 18,
            "memory_address": 35961336,
            "xrefs": [
                21676
            ]
        },
        {
            "str": "エッグクッカー温度",
            "blen": 18,
            "memory_address": 35961356,
            "xrefs": [
                16192
            ]
        },
        {
            "str": "フィレオフィッシュ",
            "blen": 18,
            "memory_address": 35961376,
            "xrefs": [
                20796
            ]
        },
        {
            "str": "クォーターパウンダー",
            "blen": 20,
            "memory_address": 35961396,
            "xrefs": [
                19524
            ]
        },
        {
            "str": "お客様が期待すること",
            "blen": 20,
            "memory_address": 35961420,
            "xrefs": [
                19532
            ]
        },
        {
            "str": "お客様が期待すること",
            "blen": 20,
            "memory_address": 35961444,
            "xrefs": [
                17412
            ]
        },
        {
            "str": "お客様が期待すること",
            "blen": 20,
            "memory_address": 35961468,
            "xrefs": [
                21652
            ]
        },
        {
            "str": "お客様が期待すること",
            "blen": 20,
            "memory_address": 35961492,
            "xrefs": [
                13596
            ]
        },
        {
            "str": "お客様が期待すること",
            "blen": 20,
            "memory_address": 35961516,
            "xrefs": [
                19956
            ]
        },
        {
            "str": "アツアツでフレッシュ",
            "blen": 20,
            "memory_address": 35961540,
            "xrefs": [
                13604
            ]
        },
        {
            "str": "（フルバット使用時）",
            "blen": 20,
            "memory_address": 35961564,
            "xrefs": [
                13708
            ]
        },
        {
            "str": "フィッシュポーション",
            "blen": 20,
            "memory_address": 35961588,
            "xrefs": [
                21220
            ]
        },
        {
            "str": "お客様が期待すること",
            "blen": 20,
            "memory_address": 35961612,
            "xrefs": [
                14020
            ]
        },
        {
            "str": "アツアツでフレッシュ",
            "blen": 20,
            "memory_address": 35961636,
            "xrefs": [
                14028
            ]
        },
        {
            "str": "お客様が期待すること",
            "blen": 20,
            "memory_address": 35961660,
            "xrefs": [
                17836
            ]
        },
        {
            "str": "お客様が期待すること",
            "blen": 20,
            "memory_address": 35961684,
            "xrefs": [
                21228
            ]
        },
        {
            "str": "お客様が期待すること",
            "blen": 20,
            "memory_address": 35961708,
            "xrefs": [
                14868
            ]
        },
        {
            "str": "エッグマックマフィン",
            "blen": 20,
            "memory_address": 35961732,
            "xrefs": [
                18252
            ]
        },
        {
            "str": "お客様が期待すること",
            "blen": 20,
            "memory_address": 35961756,
            "xrefs": [
                18260
            ]
        },
        {
            "str": "お客様が期待すること",
            "blen": 20,
            "memory_address": 35961780,
            "xrefs": [
                20380
            ]
        },
        {
            "str": "お客様が期待すること",
            "blen": 20,
            "memory_address": 35961804,
            "xrefs": [
                15292
            ]
        },
        {
            "str": "お客様が期待すること",
            "blen": 20,
            "memory_address": 35961828,
            "xrefs": [
                15716
            ]
        },
        {
            "str": "お客様が期待すること",
            "blen": 20,
            "memory_address": 35961852,
            "xrefs": [
                18684
            ]
        },
        {
            "str": "お客様が期待すること",
            "blen": 20,
            "memory_address": 35961876,
            "xrefs": [
                16988
            ]
        },
        {
            "str": "お客様が期待すること",
            "blen": 20,
            "memory_address": 35961900,
            "xrefs": [
                16140
            ]
        },
        {
            "str": "カナディアンベーコン",
            "blen": 20,
            "memory_address": 35961924,
            "xrefs": [
                16556
            ]
        },
        {
            "str": "お客様が期待すること",
            "blen": 20,
            "memory_address": 35961948,
            "xrefs": [
                19108
            ]
        },
        {
            "str": "お客様が期待すること",
            "blen": 20,
            "memory_address": 35961972,
            "xrefs": [
                16564
            ]
        },
        {
            "str": "お客様が期待すること",
            "blen": 20,
            "memory_address": 35961996,
            "xrefs": [
                20804
            ]
        },
        {
            "str": "アツアツ、新鮮な風味",
            "blen": 20,
            "memory_address": 35962020,
            "xrefs": [
                20812
            ]
        },
        {
            "str": "てりやき\nマックバーガー",
            "blen": 23,
            "memory_address": 35962404,
            "xrefs": [
                20372
            ]
        },
        {
            "str": "イングリッシュ\nマフィン",
            "blen": 23,
            "memory_address": 35962428,
            "xrefs": [
                15708
            ]
        },
        {
            "str": "ベーシックオーダーテイク",
            "blen": 24,
            "memory_address": 35962452,
            "xrefs": [
                21756
            ]
        },
        {
            "str": "温かく、しっとりしている",
            "blen": 24,
            "memory_address": 35962480,
            "xrefs": [
                14892
            ]
        },
        {
            "str": "ベーシックオーダーテイク",
            "blen": 24,
            "memory_address": 35962508,
            "xrefs": [
                21280
            ]
        },
        {
            "str": "ベーシックオーダーテイク",
            "blen": 24,
            "memory_address": 35962536,
            "xrefs": [
                21704
            ]
        },
        {
            "str": "ベーシックオーダーテイク",
            "blen": 24,
            "memory_address": 35962564,
            "xrefs": [
                21332
            ]
        },
        {
            "str": "ダブル\nクォーターパウンダー",
            "blen": 27,
            "memory_address": 35962648,
            "xrefs": [
                19948
            ]
        },
        {
            "str": "お客様のニーズを見つ\nけましょう",
            "blen": 31,
            "memory_address": 35962676,
            "xrefs": [
                14504
            ]
        },
        {
            "str": "外側はカリカリ、\n内側はしっとり",
            "blen": 31,
            "memory_address": 35962708,
            "xrefs": [
                20820
            ]
        },
        {
            "str": "シェルフライフは守られて\nいるか？",
            "blen": 33,
            "memory_address": 35962740,
            "xrefs": [
                15396
            ]
        },
        {
            "str": "オーダーが不明確な\n場合は復唱をする",
            "blen": 35,
            "memory_address": 35962776,
            "xrefs": [
                21772
            ]
        },
        {
            "str": "オーダーが不明確な\n場合は復唱をする",
            "blen": 35,
            "memory_address": 35962812,
            "xrefs": [
                21348
            ]
        },
        {
            "str": "常にスマイルで、アイ\nコンタクトを忘れない",
            "blen": 41,
            "memory_address": 35962848,
            "xrefs": [
                21764
            ]
        },
        {
            "str": "常にスマイルで、アイ\nコンタクトを忘れない",
            "blen": 41,
            "memory_address": 35962892,
            "xrefs": [
                21340
            ]
        },
        {
            "str": "原材料のホールディング\nタイムは守られているか？",
            "blen": 47,
            "memory_address": 35962936,
            "xrefs": [
                19636
            ]
        },
        {
            "str": "原材料のホールディング\nタイムは守られているか？",
            "blen": 47,
            "memory_address": 35962984,
            "xrefs": [
                20060
            ]
        },
        {
            "str": "原材料のホールディング\nタイムは守られているか？",
            "blen": 47,
            "memory_address": 35963032,
            "xrefs": [
                17940
            ]
        },
        {
            "str": "原材料のホールディング\nタイムは守られているか？",
            "blen": 47,
            "memory_address": 35963080,
            "xrefs": [
                18364
            ]
        },
        {
            "str": "原材料のホールディング\nタイムは守られているか？",
            "blen": 47,
            "memory_address": 35963128,
            "xrefs": [
                20484
            ]
        },
        {
            "str": "原材料のホールディング\nタイムは守られているか？",
            "blen": 47,
            "memory_address": 35963176,
            "xrefs": [
                18788
            ]
        },
        {
            "str": "原材料のホールディング\nタイムは守られているか？",
            "blen": 47,
            "memory_address": 35963224,
            "xrefs": [
                19212
            ]
        },
        {
            "str": "礼儀正しさと思いや\nりは、商品の価格に含\nまれています",
            "blen": 52,
            "memory_address": 35963272,
            "xrefs": [
                14452
            ]
        },
        {
            "str": "お客様の話をさえぎら\nないように、注文を最後\nまで聞く",
            "blen": 52,
            "memory_address": 35963328,
            "xrefs": [
                21288
            ]
        },
        {
            "str": "お客様の話をさえぎら\nないように、注文を最後\nまで聞く",
            "blen": 52,
            "memory_address": 35963384,
            "xrefs": [
                21712
            ]
        },
        {
            "str": "確認したら「CHECK □」をタッチ",
            "blen": 30,
            "memory_address": 35972888,
            "xrefs": [
                1324
            ]
        },
        {
            "str": "作業の前に注意事項を\n確認しましょう",
            "blen": 35,
            "memory_address": 35972920,
            "xrefs": [
                1332
            ]
        }
    ]
}