{
    "174436": "Connecting...",
    "174488": "Begin log-in",
    "174504": "Initialising download...",
    "174532": "Getting file number...",
    "174568": "Getting file list...",
    "174596": "Download %d %",
    "174616": "Download finishing...",
    "174640": "Disconnecting...",
    "174656": "Disconnected",
    "174684": "Please turn off the power.",
    "174712": "Exit Error",
    "174724": "OK",
    "174732": "No",
    "174972": "Connection Settings",
    "174984": "Send Progress Data",
    "175124": "Change Connection Method",
    "175220": "Send Progress Data",
    "175248": "Are you sure you want to update?",
    "175284": "Send Progress Data\n\nWant to connect to Wi-Fi?",
    "175352": "Updating SOC Guide\nWant to connect to Wi-Fi?",
    "175420": "Wi-Fi connection treats card\nand the DS as a set.\nWant to save the Wi-Fi user\ninformation of the DS to card\nand connect?",
    "175588": "Wi-Fi connection failed because\nuser information on DS\nand card are different.\n　\nWould you like to update\nthe user information?\nUpdating user information\nwill erase any previos data\nused over Wi-Fi connection.",
    "175872": "Last sent was \n%04d/%02d/%02d %02d:%02d",
    "175920": "Finished sending.",
    "176036": "Logging in.",
    "176252": "Sending rankings.",
    "176284": "Receiving rankings.",
    "176316": "Getting top list.",
    "176348": "Disconnected from Wi-Fi.",
    "176392": "Disconnecting from Wi-Fi.",
    "176436": "Connected to Wi-Fi.\nPlease wait.",
    "176504": "Saved Wi-Fi user information\nto this DS and card.\nFrom now on, use this\nDS for Wi-Fi connection.",
    "176668": "McDonald",
    "176684": "An error occurred.\nWi-Fi connection failed.\nPlease turn off power and try again.",
    "176792": "Error Code (%d)",
    "176812": "Communication error.",
    "176840": "No response from other party.\nThey may not be connected\nor the registration may\nnot be in their friend list.",
    "176976": "Communication error.",
    "177004": "Download failed.",
    "177036": "Communication error.",
    "177064": "Connection failed\nbecause Wi-Fi connection\nis busy or service is down.\nPlease wait and try again.",
    "177184": "Your Wi-Fi Connection ID was\nremoved due to inactivity.\nPlease see guidebook for more.",
    "177296": "The Wi-Fi connection\nservice for this\nsoftware has ended.\nThank you for using it.",
    "177384": "Unable to make connection.\nRefer to guidebook for details.",
    "177460": "Communication error.",
    "177488": "Communication error.",
    "177516": "Access point not found.\nPlease move closer\nand try again.",
    "177608": "You must agree to terms of use.\nAgree to terms of use\nin the device settings.",
    "177684": "Wireless communication is off.\nTurn on wireless communication\nin the device settings.",
    "177768": "Could not connect to\nNintendo Wi-Fi USB connector.\nCheck the USB connector\nand check the connection in\nthe Wi-Fi connection settings.",
    "177896": "No connectable access\npoint was found.\nCheck the connection destination\nin the Wi-Fi connection settings.",
    "178000": "Cannot connect because\naccess points are crowded.\nPlease wait and try again.",
    "178092": "Wi-Fi connection failed.\nCheck the connection destination\nin the Wi-Fi connection settings.",
    "178184": "Wi-Fi connection failed.\nCheck the guidebook\nfor details.",
    "178260": "Communication error.",
    "178536": "1st",
    "178548": "Top 10 Crews\n& Your Ranking",
    "178584": "Top 10 Crews",
    "178608": "Your place out of %d:",
    "178628": "Score: %4d",
    "178644": "",
    "178648": "Data of %04d/%02d/%02d %02d:%02d",
    "178688": "No ranking data received.",
    "178736": "Settings saved.",
    "179024": "You can only connect\nin a Nintendo zone.",
    "179072": "You can connect from\nother access points."
}
